<software name="punisherb" cloneof="punisher">
	<description>The Punisher (Bootleg)</description>
	<year>1993</year>
	<publisher>bootleg</publisher>
	<part name="cart">
		<dataarea name="maincpu" size="0x400000">
		<rom loadflag="load16_byte" name="c26pic.p1" offset="0x0" size="0x80000" crc="c3151563" sha1="61d3a20c25fea8a94ae6e473a87c21968867cba0" />
		<rom loadflag="load16_byte" name="c26pic.p2" offset="0x1" size="0x80000" crc="8c2593ac" sha1="4261bc72b96c3a5690df35c5d8b71524765693d9" />
		<rom loadflag="load16_byte" name="c26pic.p3" offset="0x100000" size="0x80000" crc="665a5485" sha1="c07920d110ca9c35f6cbff94a6a889c17300f994" />
		<rom loadflag="load16_byte" name="c26pic.p4" offset="0x100001" size="0x80000" crc="d7b13f39" sha1="eb7cd92b44fdef3b72672b0be6786c526421b627" />
		</dataarea>
		<dataarea name="audiocpu" size="0x28000">
		<rom name="c26.m1" offset="0x0" size="0x8000" crc="49ff4446" sha1="87af12f87a940a6c5428b4574ad44a4b54867bc3" />
		<rom loadflag="continue" offset="0x10000" size="0x18000" />
		</dataarea>
		<dataarea name="control" size="0x80">
		<rom name="punisherb.key" offset="0x0" size="0x80" crc="e1219963" sha1="ba508a09095e9a37018a5a8c3a624713d7684582" />
		</dataarea>
		<dataarea name="gfx" size="0x400000">
		<rom name="c26pic.c1" offset="0x0" size="0x40000" crc="9b9a887a" sha1="8805b36fc18837bd7c64c751b435d72b763b2235" />
		<rom loadflag="continue" offset="0x4" size="0x40000" />
		<rom name="c26pic.c2" offset="0x1" size="0x40000" crc="2b94287a" sha1="815d88e66f537e17550fc0483616f02f7126bfb1" />
		<rom loadflag="continue" offset="0x5" size="0x40000" />
		<rom name="c26pic.c3" offset="0x2" size="0x40000" crc="e9bd74f5" sha1="8ed7098c69d1c70093c99956bf82e532bd6fc7ac" />
		<rom loadflag="continue" offset="0x6" size="0x40000" />
		<rom name="c26pic.c4" offset="0x3" size="0x40000" crc="a5e1c8a4" sha1="3596265a45cf6bbf16c623f0fce7cdc65f9338ad" />
		<rom loadflag="continue" offset="0x7" size="0x40000" />
		<rom name="c26pic.c5" offset="0x200000" size="0x40000" crc="6d75a193" sha1="6c5a89517926d7ba4a925a3df800d4bdb8a6938d" />
		<rom loadflag="continue" offset="0x200004" size="0x40000" />
		<rom name="c26pic.c6" offset="0x200001" size="0x40000" crc="a3c205c1" sha1="6317cc49434dbbb9a249ddd4b50bd791803b3ebe" />
		<rom loadflag="continue" offset="0x200005" size="0x40000" />
		<rom name="c26pic.c7" offset="0x200002" size="0x40000" crc="22f2ec92" sha1="9186bfc5db71dc5b099c9a985e8fdd5710772d1c" />
		<rom loadflag="continue" offset="0x200006" size="0x40000" />
		<rom name="c26pic.c8" offset="0x200003" size="0x40000" crc="763974c9" sha1="f9b93c7cf0cb8c212fc21c57c85459b7d2e4e2fd" />
		<rom loadflag="continue" offset="0x200007" size="0x40000" />
		</dataarea>
		<dataarea name="qsound" size="0x200000">
		<rom name="c26.q1" offset="0x0" size="0x80000" crc="31fd8726" sha1="1d73a76682e9fb908db0c55b9a18163f7539fea1" />
		<rom name="c26.q2" offset="0x80000" size="0x80000" crc="980a9eef" sha1="36571381f349bc726508a7e618ba1c635ec9d271" />
		<rom name="c26.q3" offset="0x100000" size="0x80000" crc="0dd44491" sha1="903cea1d7f3120545ea3229d30fbd687d11ad68f" />
		<rom name="c26.q4" offset="0x180000" size="0x80000" crc="bed42f03" sha1="21302f7e75f9c795392a3b34e16a959fc5f6e4e9" />
		</dataarea>
	</part>
</software>
