<software name="kof2002s210" cloneof="kof2002">
	<description>Kof2002 (Unknown Hack, 2007-04-26)</description>
	<year>2007</year>
	<publisher>hack</publisher>
	<sharedfeat name="compatibility" value="MVS,AES" />
	<part name="cart" interface="neo_cart">
		<dataarea name="maincpu" width="16" endianness="big" size="0x500000">
		<rom loadflag="load16_word_swap" name="265s210.p1" offset="0x0" size="0x100000" crc="ed7211aa" sha1="0ef56df12a629eac2639ca7d5945c6c6824370b4" />
		<rom loadflag="load16_word_swap" name="265s210.p2" offset="0x100000" size="0x400000" crc="6ddcf2d5" sha1="73ed2ad018fe36f261bf2dde1c7d085638db4357" />
		</dataarea>
		<dataarea name="ymsnd:adpcma" size="0x1000000">
		<rom name="265nu.v1" offset="0x0" size="0x400000" crc="13d98607" sha1="0f1a374247992d301bc26c0bab200631a13a9f4a" />
		<rom name="265nu.v2" offset="0x400000" size="0x400000" crc="9cf74677" sha1="073e7cb00127690fdec05c19f00347ec449f15ac" />
		<rom name="265nu.v3" offset="0x800000" size="0x400000" crc="8e9448b5" sha1="c22420649c7c68a172290548cab846345c861cb0" />
		<rom name="265nu.v4" offset="0xc00000" size="0x400000" crc="067271b5" sha1="36e07da78aaf634824c98023053bef802be4e218" />
		</dataarea>
		<dataarea name="sprites" size="0x4000000">
		<rom loadflag="load16_byte" name="265s210.c1" offset="0x0" size="0x800000" crc="48d434f4" sha1="1af97af74f4cdec2bd56d99022878fe62921b4d8" />
		<rom loadflag="load16_byte" name="265s210.c2" offset="0x1" size="0x800000" crc="4d4fa9a5" sha1="1a3f7d1c0600ac6d14f26e1ea692bc658fd90309" />
		<rom loadflag="load16_byte" name="265d.c3" offset="0x1000000" size="0x800000" crc="959fad0b" sha1="63ab83ddc5f688dc8165a7ff8d262df3fcd942a2" />
		<rom loadflag="load16_byte" name="265d.c4" offset="0x1000001" size="0x800000" crc="efe6a468" sha1="2a414285e48aa948b5b0d4a9333bab083b5fb853" />
		<rom loadflag="load16_byte" name="265d.c5" offset="0x2000000" size="0x800000" crc="74bba7c6" sha1="e01adc7a4633bc0951b9b4f09abc07d728e9a2d9" />
		<rom loadflag="load16_byte" name="265d.c6" offset="0x2000001" size="0x800000" crc="e20d2216" sha1="5d28eea7b581e780b78f391a8179f1678ee0d9a5" />
		<rom loadflag="load16_byte" name="265s210.c7" offset="0x3000000" size="0x800000" crc="bd24f495" sha1="baf6c6270c6a294ef7fdf5a5857f9d02270e9e39" />
		<rom loadflag="load16_byte" name="265s210.c8" offset="0x3000001" size="0x800000" crc="23746c53" sha1="43a06f6e6314ae1aa7a90fdfcacca2c8097eebe0" />
		</dataarea>
	</part>
</software>
