<software name="sf2mix140" cloneof="sf2ce">
	<description>Street Fighter II: Dream Battle (Mix 1.4)</description>
	<year>2025</year>
	<publisher>Zero800</publisher>
	<part name="cart">
		<dataarea name="maincpu" size="0x400000">
		<rom loadflag="load16_word_swap" name="sf2mix140.p1" offset="0x0" size="0x80000" crc="c1370215" sha1="56a6d9547da973819c560db887aab77cb8aaa6c5" />
		<rom loadflag="load16_word_swap" name="sf2mix140.p2" offset="0x80000" size="0x80000" crc="5b0566c8" sha1="0e8c80b77d3b3a231c8c6092e437cbb89e8cc94e" />
		<rom loadflag="load16_word_swap" name="sf2mix140.p3" offset="0x100000" size="0x80000" crc="cb6ab274" sha1="3db8b8de22aaa90e6c8bddc04378e1edab96dce4" />
		</dataarea>
		<dataarea name="audiocpu" size="0x18000">
		<rom name="sf2mix96.m1" offset="0x0" size="0x8000" crc="a379fdc5" sha1="e9de38c13bd665698528bc102b1b16e9bdcae65b" />
		<rom loadflag="continue" offset="0x10000" size="0x8000" />
		</dataarea>
		<dataarea name="control" size="0x80">
		<rom name="sf2ce.key" offset="0x0" size="0x80" crc="35b37429" sha1="b372cce106c0900554735c207fb333ac93554ec2" />
		</dataarea>
		<dataarea name="gfx" size="0x600000">
		</dataarea>
		<dataarea name="oki" size="0x40000">
		<rom name="sf2mix96.v1" offset="0x0" size="0x20000" crc="6aa5d7fa" sha1="87cfea3a9f62653fa236f49b5b25b927cff30a02" />
		<rom name="sf2mix96.v2" offset="0x20000" size="0x20000" crc="f92f5a4f" sha1="3f1d477ab0299d2783231c3bd9983513a85b2fe6" />
		</dataarea>
	</part>
</software>
